handy_utils/__init__.py
handy_utils/cli.py
handy_utils/configuration.py
handy_utils/generate_commit.py
handy_utils/handy_utils.py
handy_utils_agni-0.1.0.dist-info/LICENSE
handy_utils_agni-0.1.0.dist-info/METADATA
handy_utils_agni-0.1.0.dist-info/WHEEL
handy_utils_agni-0.1.0.dist-info/entry_points.txt
handy_utils_agni-0.1.0.dist-info/RECORD
